annotmerge/__init__.py
annotmerge-0.0.1.dist-info/LICENCE.txt
annotmerge-0.0.1.dist-info/METADATA
annotmerge-0.0.1.dist-info/WHEEL
annotmerge-0.0.1.dist-info/top_level.txt
annotmerge-0.0.1.dist-info/RECORD
