Metadata-Version: 2.1
Name: annotmerge
Version: 0.0.1
Summary: This Library helps in merging multiple Pascall VOC Annotation file into a single Annotation
Home-page: https://github.com/connectaman/annotmerge
Author: Aman Ulla
Author-email: connectamanulla@gmail.com
License: MIT
Keywords: annotation merge
Platform: UNKNOWN
Classifier: Development Status :: 5 - Production/Stable
Classifier: Intended Audience :: Education
Classifier: Operating System :: Microsoft :: Windows :: Windows 10
Classifier: License :: OSI Approved :: MIT License
Classifier: Programming Language :: Python :: 3
Requires-Dist: os
Requires-Dist: time
Requires-Dist: logging
Requires-Dist: shutil
